paymongo/__init__.py
paymongo/constants.py
paymongo/hook.py
paymongo/payment.py
paymongo/payment_intent.py
paymongo/payment_method.py
paymongo/paymongo.py
paymongo/source.py
paymongo/urls.py
paymongo/web_hook.py
example_pkg_ccfiel-0.1.2.dev0.dist-info/LICENSE.txt
example_pkg_ccfiel-0.1.2.dev0.dist-info/METADATA
example_pkg_ccfiel-0.1.2.dev0.dist-info/WHEEL
example_pkg_ccfiel-0.1.2.dev0.dist-info/top_level.txt
example_pkg_ccfiel-0.1.2.dev0.dist-info/RECORD
